<?xml version="1.0" encoding="utf-8" ?>
<Defs>

  <ThoughtDef>
    <defName>XylMoody_Down</defName>
    <workerClass>ThoughtWorker_HediffThoughtRandom</workerClass>
    <developmentalStageFilter>Adult</developmentalStageFilter>
    <hediff>XylMoody</hediff>
    <labelInBracketsExtraForHediff>upset</labelInBracketsExtraForHediff>
    <validWhileDespawned>true</validWhileDespawned>
    <stages>
      <li>
        <label>bad mood</label>
        <description>I'm just upset today. I feel like punching something.</description>
        <baseMoodEffect>-12</baseMoodEffect>
      </li>
    </stages>
  </ThoughtDef>

  <ThoughtDef>
    <defName>XylMoody_Up</defName>
    <workerClass>ThoughtWorker_HediffThoughtRandom</workerClass>
    <developmentalStageFilter>Adult</developmentalStageFilter>
    <hediff>XylMoody</hediff>
    <labelInBracketsExtraForHediff>happy</labelInBracketsExtraForHediff>
    <validWhileDespawned>true</validWhileDespawned>
    <stages>
      <li>
        <label>good mood</label>
        <description>I'm so happy right now!</description>
        <baseMoodEffect>12</baseMoodEffect>
      </li>
    </stages>
  </ThoughtDef>

</Defs>