<?xml version="1.0" encoding="utf-8" ?>
<Defs>

  <ScenPartDef>
    <defName>ForcedXenotype</defName>
    <label>forced xenotype</label>
    <scenPartClass>XylRacesCore.ScenPart_ForcedXenotype</scenPartClass>
    <category>PlayerPawnModifier</category>
    <selectionWeight>1.0</selectionWeight>
    <summaryPriority>461</summaryPriority>
  </ScenPartDef>

  <ScenPartDef>
    <defName>StartingSlaves</defName>
    <label>start with slave(s)</label>
    <scenPartClass>XylRacesCore.ScenPart_StartingSlaves</scenPartClass>
    <category>StartingImportant</category>
    <selectionWeight>1.0</selectionWeight>
    <summaryPriority>310</summaryPriority>
  </ScenPartDef>

  <ScenPartDef MayRequire="Ludeon.Rimworld.Royalty">
    <defName>PsylinkLevels</defName>
    <label>start with psylink levels</label>
    <scenPartClass>XylRacesCore.ScenPart_PsylinkLevels</scenPartClass>
    <category>StartingImportant</category>
    <selectionWeight>1.0</selectionWeight>
    <summaryPriority>311</summaryPriority>
  </ScenPartDef>

  <ScenPartDef MayRequire="Ludeon.Rimworld.Royalty">
    <defName>Psycasts</defName>
    <label>start with psycast</label>
    <scenPartClass>XylRacesCore.ScenPart_Psycast</scenPartClass>
    <category>StartingImportant</category>
    <selectionWeight>1.0</selectionWeight>
    <summaryPriority>312</summaryPriority>
  </ScenPartDef>

</Defs>